[
  {
    "name": "IBEX-35",
    "source": "indexes/ibex35-yahoo.csv",
    "provider": "finance.yahoo.com"
  },
  {
    "name": "SP500",
    "source": "indexes/sp500-yahoo.csv",
    "provider": "finance.yahoo.com",
    "dividends": {
      "source": "indexes/sp500-dividends.csv",
      "provider": "date.yield.csv"
    }
  },
  {
    "name": "LU1290894820",
    "source": "instruments/lu1290894820-six.json",
    "provider": "www.six-group.com"
  },
  {
    "name": "CH0017810976",
    "source": "instruments/ch0017810976-six.json",
    "provider": "www.six-group.com"
  }
]
